pysatellite/__init__.py
pysatellite/cli.py
pysatellite/rocket.py
pysatellite/satellite.py
pySatellite-0.2.0.dist-info/METADATA
pySatellite-0.2.0.dist-info/WHEEL
pySatellite-0.2.0.dist-info/entry_points.txt
pySatellite-0.2.0.dist-info/top_level.txt
pySatellite-0.2.0.dist-info/RECORD
