Metadata-Version: 2.1
Name: pySatellite
Version: 0.2.0
Summary: simulate satellite tracking
Home-page: https://pySatellite.github.io
Author: pySatellite
Author-email: pySatellite@gmail.com
License: GNU General Public License (GPL)
Project-URL: Bug Tracker, https://github.com/pySatellite/pySatellite.github.io/issues
Platform: macOS
Classifier: Programming Language :: Python :: 3
Classifier: License :: OSI Approved :: GNU General Public License (GPL)
Classifier: Operating System :: OS Independent
Requires-Python: >=3.6
